img2texture/__init__.py
img2texture/__main__.py
img2texture/_cli.py
img2texture/_constants.py
img2texture/_texturizing.py
img2texture/_tiling.py
img2texture/py.typed
img2texture-1.1.2.post2.dist-info/LICENSE
img2texture-1.1.2.post2.dist-info/METADATA
img2texture-1.1.2.post2.dist-info/WHEEL
img2texture-1.1.2.post2.dist-info/entry_points.txt
img2texture-1.1.2.post2.dist-info/top_level.txt
img2texture-1.1.2.post2.dist-info/RECORD
