Metadata-Version: 2.1
Name: img2texture
Version: 1.1.2.post2
Summary: Command line utility for converting images to seamless tiles.
Home-page: https://github.com/rtmigo/img2texture#readme
Author: Artёm iG
Author-email: ortemeo@gmail.com
License: MIT
Keywords: photo,image,texture,tile,seamless
Classifier: License :: OSI Approved :: MIT License
Classifier: Programming Language :: Python :: 3.7
Classifier: Programming Language :: Python :: 3.8
Classifier: Programming Language :: Python :: 3.9
Classifier: Programming Language :: Python :: 3.10
Classifier: Programming Language :: Python :: 3.11
Classifier: Programming Language :: Python :: 3.12
Classifier: Environment :: Console
Classifier: Typing :: Typed
Classifier: Topic :: Scientific/Engineering :: Image Processing
Classifier: Topic :: Multimedia :: Graphics
Classifier: Operating System :: POSIX :: Linux
Classifier: Operating System :: MacOS
Classifier: Operating System :: Microsoft :: Windows
Requires-Python: >=3.8, <4
License-File: LICENSE
Requires-Dist: pillow >=10.0.1
